HelmSign/__init__.py
HelmSign/chart.py
HelmSign/main.py
HelmSign/py.typed
helm_sign-1.1.0.dist-info/LICENSE.md
helm_sign-1.1.0.dist-info/METADATA
helm_sign-1.1.0.dist-info/WHEEL
helm_sign-1.1.0.dist-info/entry_points.txt
helm_sign-1.1.0.dist-info/top_level.txt
helm_sign-1.1.0.dist-info/RECORD
