Metadata-Version: 2.1
Name: helm-sign
Version: 1.1.0
Summary: Gnupg based Signature Tool for Helm Charts
Home-page: https://gitlab.com/MatthiasLohr/helm-sign
Author: Matthias Lohr
Author-email: mail@mlohr.com
License: Apache License 2.0
Project-URL: Documentation, https://gitlab.com/MatthiasLohr/helm-sign/-/blob/main/README.md
Project-URL: Source, https://gitlab.com/MatthiasLohr/helm-sign
Project-URL: Tracker, https://gitlab.com/MatthiasLohr/helm-sign/issues
Classifier: Development Status :: 5 - Production/Stable
Classifier: Environment :: Console
Classifier: Intended Audience :: Developers
Classifier: Intended Audience :: Information Technology
Classifier: Intended Audience :: System Administrators
Classifier: License :: OSI Approved :: Apache Software License
Classifier: Programming Language :: Python :: 3.7
Classifier: Programming Language :: Python :: 3.8
Classifier: Programming Language :: Python :: 3.9
Classifier: Programming Language :: Python :: 3.10
Classifier: Programming Language :: Python :: 3.11
Classifier: Topic :: Security :: Cryptography
Classifier: Topic :: Software Development
Classifier: Topic :: System :: Software Distribution
Classifier: Typing :: Typed
Requires-Python: >=3.7, <4
License-File: LICENSE.md
Requires-Dist: python-gnupg ==0.5.*
Requires-Dist: PyYAML ==6.0.*
